[
  {
    "word_name": "trajectory",
    "word_means": [
      "n. 弹道,(射体在空中的)轨道,轨迹"
    ],
    "updatetime": "2023-04-26 21:44:26"
  },
  {
    "word_name": "synthesis",
    "word_means": [
      "n.(物质在动植物体内的)合成;综合;结合;综合体"
    ],
    "updatetime": "2023-04-26 21:44:08"
  },
  {
    "word_name": "straightforward",
    "word_means": [
      "adj.直截了当的; 简单的; 坦率的; 易懂的; 不复杂的; 坦诚的; 率直的",
      "adv.坦率地"
    ],
    "updatetime": "2023-04-26 09:44:52"
  },
  {
    "word_name": "slash",
    "word_means": [
      "n.斜线;斜杠;(用刀等)劈;(长而窄的)伤口;切口;砍痕;斜线号;撒尿;",
      "vt.(用利器)劈;大幅度削减;大大降低;"
    ],
    "updatetime": "2023-04-26 09:34:17"
  }
]
