[
  {
    "word_name": "gotchas",
    "word_means": [
      "gotchas公司"
    ],
    "updatetime": "2025-02-27 08:34:22",
    "from_type": "Baidu"
  },
  {
    "word_name": "Caveat",
    "word_means": [
      "告诫;知会备忘;警告,附加说明"
    ],
    "updatetime": "2025-02-27 08:33:54",
    "from_type": "Baidu"
  },
  {
    "word_name": "descendant",
    "word_means": [
      "n.后裔;后代;子孙;(由过去类似物发展来的)派生物",
      "adj.同“descendent”"
    ],
    "updatetime": "2025-02-27 08:32:47",
    "from_type": "Baidu"
  },
  {
    "word_name": "intermediate",
    "word_means": [
      "adj.中间的; 中级的; (两地、两物、两种状态等)之间的; 中等的; 适合中等程度者的",
      "n.中级学生",
      "v.起调解作用；起媒介作用"
    ],
    "updatetime": "2025-02-27 08:22:46",
    "from_type": "Baidu"
  },
  {
    "word_name": "cumbersome",
    "word_means": [
      "adj.大而笨重的;累赘的;难以携带的;缓慢复杂的;冗长的;复杂的"
    ],
    "updatetime": "2025-02-27 08:17:51",
    "from_type": "Baidu"
  }
]
