[
  {
    "word_name": "landscape",
    "word_means": [
      "n.景观; 地形，地貌; (陆上，尤指乡村的)风景，景色; <喻>全景; （形势或活动的）主要特色; (文件的)横向打印格式; 乡村风景画，乡村风景画的风格",
      "v.美化…的环境; 对…做景观美化; 给…做园林美化; 从事景观美化工作"
    ],
    "updatetime": "2024-10-20 09:59:11",
    "from_type": "Baidu"
  },
  {
    "word_name": " validate",
    "word_means": [
      "验证"
    ],
    "updatetime": "2024-10-20 09:47:28",
    "from_type": "Baidu"
  },
  {
    "word_name": " error-prone",
    "word_means": [
      "容易出错"
    ],
    "updatetime": "2024-10-20 09:46:52",
    "from_type": "Baidu"
  },
  {
    "word_name": "mayor",
    "word_means": [
      "市长"
    ],
    "updatetime": "2024-10-20 09:01:39",
    "from_type": "Baidu"
  }
]
