[
  {
    "word_name": "punishment",
    "word_means": [
      "n.惩罚; 处罚; 刑罚; 粗暴对待; 虐待"
    ],
    "updatetime": "2023-10-10 12:09:50"
  },
  {
    "word_name": "reward",
    "word_means": [
      "n.奖励; 回报; 报酬; 赏格; 悬赏金",
      "vt.奖励; 奖赏; 给以报酬"
    ],
    "updatetime": "2023-10-10 12:09:42"
  },
  {
    "word_name": "brutal",
    "word_means": [
      "adj.残酷的; 残暴的; 兽性的; 直截了当的; 冷酷的"
    ],
    "updatetime": "2023-10-10 12:05:26"
  },
  {
    "word_name": "cruel",
    "word_means": [
      "adj.残忍的; 残酷的; 残暴的; 冷酷的; (规则等)严格的, 严峻的; 引起痛苦的; 令人极痛苦的，刻毒伤人的",
      "adv.<方>极端地, 非常",
      "vt.<澳俚>搞糟，使没有成功可能"
    ],
    "updatetime": "2023-10-10 12:05:16"
  },
  {
    "word_name": "cluster",
    "word_means": [
      "n.(同类物丛生或聚集的)簇，团，束，串; (人或动物的)群，组; 辅音丛; 辅音连缀",
      "vi.群聚; 聚集"
    ],
    "updatetime": "2023-10-10 12:05:02"
  },
  {
    "word_name": "crude",
    "word_means": [
      "n.原油; 石油",
      "adj.粗糙的; 粗略的; 简略的; 大概的; 粗制的; 冒犯的，粗俗的，粗鲁的(尤其有关性的); 天然的"
    ],
    "updatetime": "2023-10-10 12:03:55"
  },
  {
    "word_name": "crucial",
    "word_means": [
      "adj.关键的; 至关重要的; 关键性的"
    ],
    "updatetime": "2023-10-10 12:03:49"
  },
  {
    "word_name": "threshold",
    "word_means": [
      "n.门槛;门口;阈;界;起始点;开端;起点;入门"
    ],
    "updatetime": "2023-10-10 11:23:56"
  },
  {
    "word_name": "humid",
    "word_means": [
      "adj.潮湿的;湿热的"
    ],
    "updatetime": "2023-10-10 11:21:25"
  },
  {
    "word_name": "humidity",
    "word_means": [
      "n.(空气中的)湿度;湿热;高温潮湿"
    ],
    "updatetime": "2023-10-10 11:21:21"
  },
  {
    "word_name": "explicit",
    "word_means": [
      "adj.明确的;清楚明白的;易于理解的;(说话)清晰的;直言的;坦率的;不隐晦的;不含糊的"
    ],
    "updatetime": "2023-10-10 09:29:27"
  },
  {
    "word_name": "override",
    "word_means": [
      "vt.优先于，压倒;比…更重要，凌驾;以权力）否决，推翻，不理会;超驰控制，超控（使自动控制暂时失效，改用手工控制）;伸展在…的上面，使（骨折端、浮冰等）重叠;践踏，压垮;骑马经过，（车辆）驶过，辗过;<美>按其销售额向（分代理商、推销员等）收取佣金（或酬金）",
      "n.超驰，超驰控制装置;撤销，推翻;<美>佣金，酬金;特许使用费;增加预算，增加费用"
    ],
    "updatetime": "2023-10-10 09:26:02"
  },
  {
    "word_name": "capital",
    "word_means": [
      "n.首都;资本;资金;国都;启动资金;财富;财产;资方;大写字母;柱顶",
      "adj.死刑的;大写的;顶好的;极好的"
    ],
    "updatetime": "2023-10-10 08:32:54"
  },
  {
    "word_name": "writeup",
    "word_means": [
      "writeup      n.    评论（同 write-up）"
    ],
    "updatetime": "2023-10-10 08:20:53"
  },
  {
    "word_name": "inclusion",
    "word_means": [
      "n.(被)包括，包含;被包括的人(或事物);"
    ],
    "updatetime": "2023-10-10 08:20:35"
  },
  {
    "word_name": "quiz",
    "word_means": [
      "n. 测验,知识竞赛,智力游戏;",
      "vt. 测验(学生),询问,查问,盘问;"
    ],
    "updatetime": "2023-10-10 06:47:19"
  },
  {
    "word_name": "orator",
    "word_means": [
      "n. 雄辩家,讲演者,善于演说的人"
    ],
    "updatetime": "2023-10-10 06:47:11"
  },
  {
    "word_name": "engage with",
    "word_means": [
      "交战"
    ],
    "updatetime": "2023-10-10 06:46:50"
  },
  {
    "word_name": "pronounce",
    "word_means": [
      "v. 发音,读(音),正式宣布(或公布、授予等)"
    ],
    "updatetime": "2023-10-10 06:46:18"
  },
  {
    "word_name": "pronunciation",
    "word_means": [
      "n. (某人的)发音,读音"
    ],
    "updatetime": "2023-10-10 06:46:00"
  },
  {
    "word_name": "emotive",
    "word_means": [
      "adj. 激动人心的,有感染力的,激起感情的"
    ],
    "updatetime": "2023-10-10 06:45:44"
  },
  {
    "word_name": "vague",
    "word_means": [
      "adj. 模糊的,含糊的,不明确的,(思想上)不清楚的,茫然的,粗略的,心不在焉的,糊涂的,不具体的,不详细的"
    ],
    "updatetime": "2023-10-10 06:45:08"
  },
  {
    "word_name": "Pronunciation",
    "word_means": [
      "n. (某人的)发音,读音"
    ],
    "updatetime": "2023-10-10 06:45:02"
  },
  {
    "word_name": "affection",
    "word_means": [
      "n. 感情,爱情,喜爱,钟爱"
    ],
    "updatetime": "2023-10-10 06:42:17"
  },
  {
    "word_name": "slogan",
    "word_means": [
      "n. 口号,标语"
    ],
    "updatetime": "2023-10-10 06:42:09"
  },
  {
    "word_name": "contagious",
    "word_means": [
      "adj. 传染性的,(疾病)接触传染的,患接触性传染病"
    ],
    "updatetime": "2023-10-10 06:41:42"
  },
  {
    "word_name": "infectious",
    "word_means": [
      "adj. 传染性的，感染的(尤指通过呼吸),患有传染病,有传染力"
    ],
    "updatetime": "2023-10-10 06:40:20"
  },
  {
    "word_name": "appealing",
    "word_means": [
      "adj. 有吸引力的,吸引人的,恳求的,有感染力的,可怜的,令人感兴趣的,希望同情的;",
      "v. 上诉,呼吁,申诉,吁请,有吸引力,恳求,有感染力,引起兴趣;",
      "appeal的现在分词;"
    ],
    "updatetime": "2023-10-10 06:40:16"
  },
  {
    "word_name": "unquestionable",
    "word_means": [
      "adj. 无疑的,无可非议的,确实的"
    ],
    "updatetime": "2023-10-10 06:35:22"
  },
  {
    "word_name": "persuasive",
    "word_means": [
      "adj. 有说服力的，能使人信服的,劝说的，劝诱的;",
      "n. （贿赂等）用于劝诱人的事物，引诱物;"
    ],
    "updatetime": "2023-10-10 06:35:13"
  },
  {
    "word_name": "disastrous",
    "word_means": [
      "adj. 灾难性的,完全失败的,极糟糕的"
    ],
    "updatetime": "2023-10-10 06:33:50"
  },
  {
    "word_name": "abused",
    "word_means": [
      "v. 滥用(以致危害健康),滥用，妄用(权力、所知所闻),虐待,性虐待,伤害;",
      "adj. （尤指药物）滥用的；受虐的;",
      "abuse的过去分词和过去式;"
    ],
    "updatetime": "2023-10-10 06:33:39"
  },
  {
    "word_name": "truthful",
    "word_means": [
      "adj. 真实的,诚实的,诚实,如实的,讲真话,坦率"
    ],
    "updatetime": "2023-10-10 06:33:09"
  },
  {
    "word_name": "come into play",
    "word_means": [
      " （使）开始起作用,（使）开始活动,（使）投入使用"
    ],
    "updatetime": "2023-10-10 06:32:12"
  },
  {
    "word_name": "cheat",
    "word_means": [
      "v. (尤指在游戏、比赛、考试等中)作弊，舞弊,欺骗,蒙骗,对某人不忠(或不贞),与他人有秘密性关系;",
      "n. (尤指游戏中的)作弊者，骗子,欺诈行为,(电脑游戏的)秘技，欺骗程序，作弊软件,欺骗手段;"
    ],
    "updatetime": "2023-10-10 06:31:49"
  },
  {
    "word_name": "mistakenly",
    "word_means": [
      "adv. 错误地"
    ],
    "updatetime": "2023-10-10 06:31:27"
  },
  {
    "word_name": "mistaken",
    "word_means": [
      "v. 弄错,误解,误会,看错;",
      "adj. 错误,被误解的,不正确,判断错误的;",
      "mistake的过去分词;"
    ],
    "updatetime": "2023-10-10 06:30:44"
  },
  {
    "word_name": "clerk",
    "word_means": [
      "n. 职员,店员,(议会、法院等的)书记员,文书,簿记员,旅馆服务台接待员;",
      "vi. 当职员(或文书、书记员);"
    ],
    "updatetime": "2023-10-10 06:30:39"
  },
  {
    "word_name": "credit",
    "word_means": [
      "n. 信用,学分,贷款,赊购,赊欠,(从银行借的)借款,(借钱偿还的)信誉,结余,存款金额，贷记,有权索要的款项,赞扬,为…赢得荣誉的人（或事物）,片头字幕，片尾字幕;",
      "vt. (给银行账户)存入金额,把…记入贷方,贷记(银行账户),认为是…的功劳,把…归于,认为…有(良好的品质或特点),认为…属（某种类或性质）,相信;"
    ],
    "updatetime": "2023-10-10 06:29:43"
  },
  {
    "word_name": "affair",
    "word_means": [
      "n. 公共事务,政治事务,事件,事情,(尤指已婚男女的)私通，风流韵事,私人业务,个人的事,不寻常之物"
    ],
    "updatetime": "2023-10-10 06:27:56"
  },
  {
    "word_name": "physicist",
    "word_means": [
      "n. 物理学家,物理学研究者"
    ],
    "updatetime": "2023-10-10 06:27:12"
  },
  {
    "word_name": "physician",
    "word_means": [
      "n. 医师,(尤指)内科医生"
    ],
    "updatetime": "2023-10-10 06:26:57"
  },
  {
    "word_name": "psychologist",
    "word_means": [
      "n. 心理学家,心理学研究者"
    ],
    "updatetime": "2023-10-10 06:26:22"
  },
  {
    "word_name": "philosopher",
    "word_means": [
      "n. 哲学家,深思的人,善于思考的人"
    ],
    "updatetime": "2023-10-10 06:25:55"
  },
  {
    "word_name": "philosophy",
    "word_means": [
      "n. 哲学,人生哲学,哲学体系,思想体系,生活的信条(或态度)"
    ],
    "updatetime": "2023-10-10 06:25:47"
  },
  {
    "word_name": "physics",
    "word_means": [
      "n. 物理学;",
      "v. 处罚,治愈,给…吃药,给…吃泻药;",
      "physic的第三人称单数;"
    ],
    "updatetime": "2023-10-10 06:25:37"
  },
  {
    "word_name": "psychology",
    "word_means": [
      "n. 心理,心理学,心理特征,心理影响"
    ],
    "updatetime": "2023-10-10 06:25:32"
  },
  {
    "word_name": "nurture",
    "word_means": [
      "vt. 培养,养育,支持,帮助,扶持,助长,养护,滋长;",
      "n. 养育,培养;"
    ],
    "updatetime": "2023-10-10 06:24:06"
  },
  {
    "word_name": "nutrition",
    "word_means": [
      "n. 营养,滋养,营养的补给"
    ],
    "updatetime": "2023-10-10 06:21:45"
  },
  {
    "word_name": "nourish",
    "word_means": [
      "vt. 滋养,培养，助长(情绪、观点等),养育,抚养"
    ],
    "updatetime": "2023-10-10 06:21:20"
  },
  {
    "word_name": "score your first triumph",
    "word_means": [
      "取得你的第一次胜利"
    ],
    "updatetime": "2023-10-10 06:20:18"
  },
  {
    "word_name": "score",
    "word_means": [
      "n. 分数,(游戏或比赛中的)得分,比分,(考试中的)成绩,总谱,（电影或戏剧的）配乐,20个,大量,刻痕,实情;",
      "v. (在游戏、比赛或考试中)得分,(在游戏或比赛中)记分,评分,分值是,获得胜利,编总谱,（在物体表面）划下痕迹，刻出记号;"
    ],
    "updatetime": "2023-10-10 06:19:46"
  }
]
